oclgrind_binary_distribution/__init__.py
oclgrind_binary_distribution/.libs/liboclgrind-3cb40ae3.so
oclgrind_binary_distribution/.libs/include/WorkItem.h
oclgrind_binary_distribution/.libs/include/Queue.h
oclgrind_binary_distribution/.libs/include/opencl-c.h
oclgrind_binary_distribution/.libs/include/common.h
oclgrind_binary_distribution/.libs/include/Memory.h
oclgrind_binary_distribution/.libs/include/opencl-c-2.0-32.pch
oclgrind_binary_distribution/.libs/include/WorkGroup.h
oclgrind_binary_distribution/.libs/include/Context.h
oclgrind_binary_distribution/.libs/include/opencl-c-base.h
oclgrind_binary_distribution/.libs/include/opencl-c-2.0-64.pch
oclgrind_binary_distribution/.libs/include/Program.h
oclgrind_binary_distribution/.libs/include/opencl-c-1.2-32.pch
oclgrind_binary_distribution/.libs/include/Kernel.h
oclgrind_binary_distribution/.libs/include/opencl-c-1.2-64.pch
oclgrind_binary_distribution/.libs/include/KernelInvocation.h
oclgrind_binary_distribution/.libs/include/Plugin.h
oclgrind_binary_distribution/.libs/share/oclgrind/licenses/OCLGRIND_LICENSE.txt
oclgrind_binary_distribution/.libs/share/oclgrind/licenses/LLVM_LICENSE.txt
pyopencl/.libs/liboclgrind-rt-icd-9fd49082.so
pyopencl/.libs/oclgrind.icd
oclgrind_binary_distribution-19.10.dist-info/WHEEL
oclgrind_binary_distribution-19.10.dist-info/METADATA
oclgrind_binary_distribution-19.10.dist-info/top_level.txt
oclgrind_binary_distribution-19.10.dist-info/RECORD
