Metadata-Version: 2.1
Name: oclgrind-binary-distribution
Version: 19.10
Summary: Oclgrind Binary Distribution to be used with PyOpenCL
Home-page: https://github.com/isuruf/pocl-binary-distribution
Author: Isuru Fernando
Author-email: isuruf@gmail.com
